neurotrace/__init__.py
neurotrace/core/__init__.py
neurotrace/core/constants.py
neurotrace/core/graph_memory.py
neurotrace/core/llm_tasks.py
neurotrace/core/memory.py
neurotrace/core/schema.py
neurotrace/core/utils.py
neurotrace/core/vector_memory.py
neurotrace/core/adapters/__init__.py
neurotrace/core/adapters/langchain_adapter.py
neurotrace/core/adapters/vector_db_adapter.py
neurotrace/core/hippocampus/__init__.py
neurotrace/core/hippocampus/ltm.py
neurotrace/core/hippocampus/memory_orchestrator.py
neurotrace/core/hippocampus/stm.py
neurotrace/core/tools/__init__.py
neurotrace/core/tools/factory.py
neurotrace/core/tools/memory.py
neurotrace/core/tools/system.py
neurotrace/core/tools/vector.py
neurotrace/neurotrace_logging/__init__.py
neurotrace/neurotrace_logging/logger_factory.py
neurotrace/neurotrace_logging/memory_logger.py
neurotrace/prompts/__init__.py
neurotrace/prompts/task_prompts.py
neurotrace/prompts/tools/__init__.py
neurotrace/prompts/tools/save_memory.md
neurotrace/prompts/tools/search_memory.md
neurotrace-1.0.3.dist-info/METADATA
neurotrace-1.0.3.dist-info/WHEEL
neurotrace-1.0.3.dist-info/top_level.txt
neurotrace-1.0.3.dist-info/RECORD
