Metadata-Version: 2.4
Name: neurotrace
Version: 1.0.3
Summary: Memory of your Agent 📝
Project-URL: Homepage, https://github.com/foo290/neurotrace
Project-URL: Repository, https://github.com/foo290/neurotrace
Project-URL: Issues, https://github.com/foo290/neurotrace/issues
Project-URL: Documentation, https://foo290.github.io/neurotrace
Requires-Python: >=3.11
Requires-Dist: black>=25.1.0
Requires-Dist: chromadb>=1.0.15
Requires-Dist: google-generativeai>=0.8.5
Requires-Dist: ipython>=9.3.0
Requires-Dist: isort>=6.0.1
Requires-Dist: langchain-community>=0.3.25
Requires-Dist: langchain-google-genai>=2.0.10
Requires-Dist: langchain-tavily>=0.2.1
Requires-Dist: langchain[google-genai]>=0.3.25
Requires-Dist: langgraph>=0.4.8
Requires-Dist: mkdocs>=1.6.1
Requires-Dist: mkdocs-awesome-pages-plugin>=2.10.1
Requires-Dist: mkdocs-material>=9.6.15
Requires-Dist: mkdocstrings>=0.29.1
Requires-Dist: mkdocstrings-python>=1.16.12
Requires-Dist: neo4j>=5.28.1
Requires-Dist: networkx>=3.5
Requires-Dist: pre-commit>=4.2.0
Requires-Dist: pytest>=8.4.1
Requires-Dist: pytest-cov>=6.2.1
Requires-Dist: scikit-learn>=1.7.0
Requires-Dist: sentence-transformers>=5.0.0
Requires-Dist: tavily-python>=0.7.9
